MANIFEST.in
NEWS.txt
README.rst
setup.py
src/pythonselect/__init__.py
src/pythonselect/base.py
src/pythonselect/command.py
src/pythonselect.egg-info/PKG-INFO
src/pythonselect.egg-info/SOURCES.txt
src/pythonselect.egg-info/dependency_links.txt
src/pythonselect.egg-info/entry_points.txt
src/pythonselect.egg-info/not-zip-safe
src/pythonselect.egg-info/top_level.txt