Metadata-Version: 1.0
Name: pythonselect
Version: 1.0
Summary: A tool to set current Python version (currently MacOSX only)
Home-page: http://github.com/ActiveState/pythonselect
Author: srid
Author-email: srid@nearfar.org
License: MIT
Platform: UNKNOWN
Classifier: Development Status :: 4 - Beta
Classifier: Environment :: Console
Classifier: Environment :: MacOS X
Classifier: Intended Audience :: Developers
Classifier: Intended Audience :: System Administrators
Classifier: License :: OSI Approved :: MIT License
Classifier: Operating System :: MacOS :: MacOS X
Classifier: Programming Language :: Python
Classifier: Topic :: System
Classifier: Topic :: Utilities
